{
    "backend": "api-server-nodejs",
    "db_name": "",
    "db_pass": "",
    "db_type": "sqlite",
    "db_user": "",
    "dbms": "1",
    "description": "generated product",
    "design": "horizon-ui",
    "docker": "0",
    "err_code": 0,
    "frontend": "react",
    "github_repo": "https://github.com/appseed-projects/cdc61ebf-bbf8-4512-9f82-923c6712f5d9",
    "heroku": "0",
    "pattern": "fullstack",
    "pro": "0",
    "task_id": "cdc61ebf-bbf8-4512-9f82-923c6712f5d9",
    "task_info": "Upload Sources [0%] - 180 files",
    "task_output": "cdc61ebf-bbf8-4512-9f82-923c6712f5d9.zip",
    "task_result": "SUCCESS",
    "task_state": "RUNNING",
    "task_ts_end": "2022-06-29-12-12-02",
    "task_ts_start": "2022-06-29-12-12-00"
}